<IndoorNavigation>
	<SegmentInfo>
		<SegmentID>099001</SegmentID>
		<from>118.91118174,32.11690474,9,099</from>
		<to>118.91118224,32.11688328,9,099</to>
	</SegmentInfo>
	<SegmentInfo>
		<SegmentID>099002</SegmentID>
		<from>118.91118174,32.11690474,9,099</from>
		<to>118.91120927,32.11690551,9,099</to>
	</SegmentInfo>
	<SegmentInfo>
		<SegmentID>099003</SegmentID>
		<from>118.91120927,32.11690551,9,099</from>
		<to>118.91120977,32.11688405,9,099</to>
	</SegmentInfo>
	<SegmentInfo>
		<SegmentID>099004</SegmentID>
		<from>118.91120927,32.11690551,9,099</from>
		<to>118.91124947,32.11690664,9,099</to>
	</SegmentInfo>
	<SegmentInfo>
		<SegmentID>099005</SegmentID>
		<from>118.91124947,32.11690664,9,099</from>
		<to>118.91124998,32.11688483,9,099</to>
	</SegmentInfo>
	<SegmentInfo>
		<SegmentID>099006</SegmentID>
		<from>118.91124947,32.11690664,9,099</from>
		<to>118.91127410,32.11690734,9,099</to>
	</SegmentInfo>
	<SegmentInfo>
		<SegmentID>099007</SegmentID>
		<from>118.91127410,32.11690734,9,099</from>
		<to>118.91127459,32.11688629,9,099</to>
	</SegmentInfo>
	<SegmentInfo>
		<SegmentID>099008</SegmentID>
		<from>118.91127410,32.11690734,9,099</from>
		<to>118.91129844,32.11690803,9,099</to>
	</SegmentInfo>
	<SegmentInfo>
		<SegmentID>099009</SegmentID>
		<from>118.91129844,32.11690803,9,099</from>
		<to>118.91129894,32.11688697,9,099</to>
	</SegmentInfo>
	<SegmentInfo>
		<SegmentID>099010</SegmentID>
		<from>118.91129844,32.11690803,9,099</from>
		<to>118.91133690,32.11690911,9,099</to>
	</SegmentInfo>
	<SegmentInfo>
		<SegmentID>099011</SegmentID>
		<from>118.91133690,32.11690911,9,099</from>
		<to>118.91133738,32.11688857,9,099</to>
	</SegmentInfo>
	<SegmentInfo>
		<SegmentID>099012</SegmentID>
		<from>118.91133690,32.11690911,9,099</from>
		<to>118.91136180,32.11690981,9,099</to>
	</SegmentInfo>
	<SegmentInfo>
		<SegmentID>099013</SegmentID>
		<from>118.91136180,32.11690981,9,099</from>
		<to>118.91136226,32.11689004,9,099</to>
	</SegmentInfo>
	<SegmentInfo>
		<SegmentID>099014</SegmentID>
		<from>118.91136180,32.11690981,9,099</from>
		<to>118.91136772,32.11690998,9,099</to>
	</SegmentInfo>
	<SegmentInfo>
		<SegmentID>099015</SegmentID>
		<from>118.91136772,32.11690998,9,099</from>
		<to>118.91138643,32.11691051,9,099</to>
	</SegmentInfo>
	<SegmentInfo>
		<SegmentID>099016</SegmentID>
		<from>118.91138643,32.11691051,9,099</from>
		<to>118.91138690,32.11688996,9,099</to>
	</SegmentInfo>
	<SegmentInfo>
		<SegmentID>099017</SegmentID>
		<from>118.91118128,32.11692413,9,099</from>
		<to>118.91117169,32.11692367,9,099</to>
	</SegmentInfo>
	<SegmentInfo>
		<SegmentID>099018</SegmentID>
		<from>118.91118128,32.11692413,9,099</from>
		<to>118.91118174,32.11690474,9,099</to>
	</SegmentInfo>
	<SegmentInfo>
		<SegmentID>099019</SegmentID>
		<from>118.91136608,32.11698042,9,099</from>
		<to>118.91136772,32.11690998,9,099</to>
	</SegmentInfo>
	<SegmentInfo>
		<SegmentID>099020</SegmentID>
		<from>118.91140087,32.11698139,1,099</from>
		<to>118.91136608,32.11698042,9,099</to>
	</SegmentInfo>
	<SegmentInfo>
		<SegmentID>099021</SegmentID>
		<from>118.91157953,32.11698644,9,099</from>
		<to>118.91140087,32.11698139,1,099</to>
	</SegmentInfo>
	<SegmentInfo>
		<SegmentID>099022</SegmentID>
		<from>118.91118002,32.11697816,9,099</from>
		<to>118.91117002,32.11697769,9,099</to>
	</SegmentInfo>
	<SegmentInfo>
		<SegmentID>099023</SegmentID>
		<from>118.91118002,32.11697816,9,099</from>
		<to>118.91118128,32.11692413,9,099</to>
	</SegmentInfo>
	<SegmentInfo>
		<SegmentID>099024</SegmentID>
		<from>118.91112147,32.11706803,9,099</from>
		<to>118.91112148,32.11704080,9,099</to>
	</SegmentInfo>
	<SegmentInfo>
		<SegmentID>099025</SegmentID>
		<from>118.91112116,32.11708106,9,099</from>
		<to>118.91112147,32.11706803,9,099</to>
	</SegmentInfo>
	<SegmentInfo>
		<SegmentID>099026</SegmentID>
		<from>118.91117754,32.11708476,9,099</from>
		<to>118.91112116,32.11708106,9,099</to>
	</SegmentInfo>
	<SegmentInfo>
		<SegmentID>099027</SegmentID>
		<from>118.91117754,32.11708476,9,099</from>
		<to>118.91118002,32.11697816,9,099</to>
	</SegmentInfo>
	<SegmentInfo>
		<SegmentID>099028</SegmentID>
		<from>118.91136608,32.11698042,9,099</from>
		<to>118.91136218,32.11714748,9,099</to>
	</SegmentInfo>
	<SegmentInfo>
		<SegmentID>099029</SegmentID>
		<from>118.91136218,32.11714748,9,099</from>
		<to>118.91141547,32.11714898,9,099</to>
	</SegmentInfo>
	<SegmentInfo>
		<SegmentID>099030</SegmentID>
		<from>118.91117593,32.11715367,9,099</from>
		<to>118.91115020,32.11715294,9,099</to>
	</SegmentInfo>
	<SegmentInfo>
		<SegmentID>099031</SegmentID>
		<from>118.91117593,32.11715367,9,099</from>
		<to>118.91117754,32.11708476,9,099</to>
	</SegmentInfo>
	<SegmentInfo>
		<SegmentID>099032</SegmentID>
		<from>118.91136218,32.11714748,9,099</from>
		<to>118.91136191,32.11715906,9,099</to>
	</SegmentInfo>
	<SegmentInfo>
		<SegmentID>099033</SegmentID>
		<from>118.91136191,32.11715906,9,099</from>
		<to>118.91128884,32.11715734,9,099</to>
	</SegmentInfo>
	<SegmentInfo>
		<SegmentID>099034</SegmentID>
		<from>118.91127096,32.11715693,9,099</from>
		<to>118.91127146,32.11713537,9,099</to>
	</SegmentInfo>
	<SegmentInfo>
		<SegmentID>099035</SegmentID>
		<from>118.91128884,32.11715734,9,099</from>
		<to>118.91127096,32.11715693,9,099</to>
	</SegmentInfo>
	<SegmentInfo>
		<SegmentID>099036</SegmentID>
		<from>118.91122870,32.11715598,9,099</from>
		<to>118.91117593,32.11715367,9,099</to>
	</SegmentInfo>
	<SegmentInfo>
		<SegmentID>099037</SegmentID>
		<from>118.91127096,32.11715693,9,099</from>
		<to>118.91122870,32.11715598,9,099</to>
	</SegmentInfo>
	<SegmentInfo>
		<SegmentID>099038</SegmentID>
		<from>118.91136191,32.11715906,9,099</from>
		<to>118.91136160,32.11717235,9,099</to>
	</SegmentInfo>
	<SegmentInfo>
		<SegmentID>099039</SegmentID>
		<from>118.91122870,32.11715598,9,099</from>
		<to>118.91122825,32.11717540,9,099</to>
	</SegmentInfo>
	<SegmentInfo>
		<SegmentID>099040</SegmentID>
		<from>118.91128884,32.11715734,9,099</from>
		<to>118.91128838,32.11717709,9,099</to>
	</SegmentInfo>
	<SegmentInfo>
		<SegmentID>099041</SegmentID>
		<from>118.91136160,32.11717235,9,099</from>
		<to>118.91136142,32.11717984,9,099</to>
	</SegmentInfo>
	<SegmentInfo>
		<SegmentID>099042</SegmentID>
		<from>118.91139778,32.11719653,9,099</from>
		<to>118.91141396,32.11719648,9,099</to>
	</SegmentInfo>
	<SegmentInfo>
		<SegmentID>099043</SegmentID>
		<from>118.91112147,32.11706803,9,099</from>
		<to>118.911099,32.117061,2,099</to>
	</SegmentInfo>
	<SegmentInfo>
		<SegmentID>099044</SegmentID>
		<from>118.91112148,32.11704080,9,099</from>
		<to>118.911099,32.117033,2,099</to>
	</SegmentInfo>
	<SegmentInfo>
		<SegmentID>099045</SegmentID>
		<from>118.91139832,32.11717290,9,099</from>
		<to>118.91141306,32.11717312,9,099</to>
	</SegmentInfo>
	<SegmentInfo>
		<SegmentID>099046</SegmentID>
		<from>118.91136160,32.11717235,9,099</from>
		<to>118.91139832,32.11717290,9,099</to>
	</SegmentInfo>
	<SegmentInfo>
		<SegmentID>099047</SegmentID>
		<from>118.91139832,32.11717290,9,099</from>
		<to>118.91139778,32.11719653,9,099</to>
	</SegmentInfo>
	<SegmentInfo>
		<SegmentID>099048</SegmentID>
		<from>118.911099,32.117061,2,099</from>
		<to>118.911099,32.117061,2,100</to>
	</SegmentInfo>
	<SegmentInfo>
		<SegmentID>099049</SegmentID>
		<from>118.911099,32.117061,2,099</from>
		<to>118.911099,32.117033,2,100</to>
	</SegmentInfo>
</IndoorNavigation>
